nydus/__init__.py
nydus/conf.py
nydus/testutils.py
nydus/utils.py
nydus/contrib/__init__.py
nydus/contrib/ketama.py
nydus/db/__init__.py
nydus/db/base.py
nydus/db/exceptions.py
nydus/db/map.py
nydus/db/promise.py
nydus/db/backends/__init__.py
nydus/db/backends/base.py
nydus/db/backends/memcache.py
nydus/db/backends/pycassa.py
nydus/db/backends/redis.py
nydus/db/backends/riak.py
nydus/db/backends/thoonk.py
nydus/db/routers/__init__.py
nydus/db/routers/base.py
nydus/db/routers/keyvalue.py
nydus/db/routers/redis.py
nydus-0.10.8.dist-info/dependency_links.txt
nydus-0.10.8.dist-info/DESCRIPTION.rst
nydus-0.10.8.dist-info/METADATA
nydus-0.10.8.dist-info/metadata.json
nydus-0.10.8.dist-info/RECORD
nydus-0.10.8.dist-info/top_level.txt
nydus-0.10.8.dist-info/WHEEL
tests/nydus/__init__.py
tests/nydus/db/__init__.py
tests/nydus/db/backends/__init__.py
tests/nydus/db/backends/memcache/__init__.py
tests/nydus/db/backends/memcache/tests.py
tests/nydus/db/backends/pycassa/__init__.py
tests/nydus/db/backends/pycassa/tests.py
tests/nydus/db/backends/redis/__init__.py
tests/nydus/db/backends/redis/tests.py
tests/nydus/db/backends/riak/__init__.py
tests/nydus/db/backends/riak/tests.py
tests/nydus/db/backends/thoonk/__init__.py
tests/nydus/db/backends/thoonk/tests.py
tests/nydus/db/connections/__init__.py
tests/nydus/db/connections/tests.py
tests/nydus/db/routers/__init__.py
tests/nydus/db/routers/tests.py
