Metadata-Version: 2.0
Name: nydus
Version: 0.10.8
Summary: Connection utilities
Home-page: https://github.com/disqus/nydus
Author: DISQUS
Author-email: opensource@disqus.com
License: Apache License 2.0
Platform: UNKNOWN
Classifier: Intended Audience :: Developers
Classifier: Intended Audience :: System Administrators
Classifier: Operating System :: OS Independent
Classifier: Topic :: Software Development
Provides-Extra: test
Requires-Dist: mock; extra == 'test'
Requires-Dist: nose; extra == 'test'
Requires-Dist: pycassa; extra == 'test'
Requires-Dist: pylibmc; extra == 'test'
Requires-Dist: redis; extra == 'test'
Requires-Dist: riak; extra == 'test'
Requires-Dist: thoonk; extra == 'test'
Requires-Dist: unittest2; extra == 'test'
